Metadata-Version: 2.1
Name: notion-df
Version: 0.0.5
Summary: Notion-DF: Seamlessly Connecting Notion Database with Pandas DataFrame
Home-page: https://github.com/lolipopshock/notion-df
Author: Zejiang Shen
Author-email: zejiangshen@gmail.com
License: MIT
Platform: UNKNOWN
Requires-Python: >=3.6
License-File: LICENSE
Requires-Dist: notion-client (>=0.8.0)
Requires-Dist: pydantic (~=1.9.0)
Requires-Dist: pandas
Requires-Dist: dataclasses
Provides-Extra: dev
Requires-Dist: black (==21.12b0) ; extra == 'dev'
Requires-Dist: pytest ; extra == 'dev'
